postgresqlfacil/__init__.py
postgresqlfacil/postgresqlfacil.py
postgresqlfacil-0.2.2.dist-info/LICENSE
postgresqlfacil-0.2.2.dist-info/METADATA
postgresqlfacil-0.2.2.dist-info/WHEEL
postgresqlfacil-0.2.2.dist-info/RECORD
