Metadata-Version: 2.1
Name: postgresqlfacil
Version: 0.2.2
Summary: O pacote PostgreSQLFacil oferece uma interface simplificada para interagir com o banco de dados PostgreSQL, abstraindo as operações comuns de SELECT, INSERT, UPDATE e DELETE em métodos convenientes e com integrações em DataFrames do pandas.
License: MIT
Author: eduardo.barreto
Author-email: edugobarreto@gmail.com
Requires-Python: >=3.8,<4
Classifier: License :: OSI Approved :: MIT License
Classifier: Programming Language :: Python :: 3
Classifier: Programming Language :: Python :: 3.8
Classifier: Programming Language :: Python :: 3.9
Classifier: Programming Language :: Python :: 3.10
Classifier: Programming Language :: Python :: 3.11
Classifier: Programming Language :: Python :: 3.12
Provides-Extra: psycopg2
Provides-Extra: psycopg2-binary
Requires-Dist: pandas (>=2.0.3,<3.0.0)
